shared_ndarray/__init__.py
shared_ndarray/shared_ndarray.py
shared_ndarray/test_shared_ndarray.py
shared_ndarray-1.1.1.dist-info/DESCRIPTION.rst
shared_ndarray-1.1.1.dist-info/METADATA
shared_ndarray-1.1.1.dist-info/RECORD
shared_ndarray-1.1.1.dist-info/WHEEL
shared_ndarray-1.1.1.dist-info/metadata.json
shared_ndarray-1.1.1.dist-info/top_level.txt
