Metadata-Version: 1.1
Name: shared-ndarray
Version: 1.1.1
Summary: A pickleable wrapper for sharing NumPy ndarrays between processes using POSIX shared memory.
Home-page: https://github.com/crowsonkb/shared_ndarray
Author: Katherine Crowson
Author-email: crowsonkb@gmail.com
License: MIT
Keywords: numpy ndarray array shared memory shm
Platform: UNKNOWN
Classifier: Development Status :: 5 - Production/Stable
Classifier: Intended Audience :: Developers
Classifier: Intended Audience :: Science/Research
Classifier: License :: OSI Approved :: MIT License
Classifier: Programming Language :: Python :: 2
Classifier: Programming Language :: Python :: 3
Classifier: Topic :: Scientific/Engineering
